aiida_gromacs/__init__.py
aiida_gromacs/helpers.py
aiida_gromacs/calculations/__init__.py
aiida_gromacs/calculations/editconf.py
aiida_gromacs/calculations/genericMD.py
aiida_gromacs/calculations/genion.py
aiida_gromacs/calculations/grompp.py
aiida_gromacs/calculations/make_ndx.py
aiida_gromacs/calculations/mdrun.py
aiida_gromacs/calculations/pdb2gmx.py
aiida_gromacs/calculations/solvate.py
aiida_gromacs/cli/createarchive.py
aiida_gromacs/cli/editconf.py
aiida_gromacs/cli/genericMD.py
aiida_gromacs/cli/genion.py
aiida_gromacs/cli/grompp.py
aiida_gromacs/cli/make_ndx.py
aiida_gromacs/cli/mdrun.py
aiida_gromacs/cli/pdb2gmx.py
aiida_gromacs/cli/solvate.py
aiida_gromacs/commands/provenance.py
aiida_gromacs/data/__init__.py
aiida_gromacs/data/editconf.py
aiida_gromacs/data/genion.py
aiida_gromacs/data/grompp.py
aiida_gromacs/data/make_ndx.py
aiida_gromacs/data/mdrun.py
aiida_gromacs/data/pdb2gmx.py
aiida_gromacs/data/plumed_input.py
aiida_gromacs/data/solvate.py
aiida_gromacs/parsers/__init__.py
aiida_gromacs/parsers/editconf.py
aiida_gromacs/parsers/genericMD.py
aiida_gromacs/parsers/genion.py
aiida_gromacs/parsers/grompp.py
aiida_gromacs/parsers/make_ndx.py
aiida_gromacs/parsers/mdrun.py
aiida_gromacs/parsers/pdb2gmx.py
aiida_gromacs/parsers/solvate.py
aiida_gromacs/utils/displayprovenance.py
aiida_gromacs/utils/fileparsers.py
aiida_gromacs/utils/inputFile_utils.py
aiida_gromacs/utils/inspectdb.py
aiida_gromacs/utils/querydb.py
aiida_gromacs/utils/searchprevious.py
aiida_gromacs/utils/topfile_utils.py
aiida_gromacs/workflows/__init__.py
aiida_gromacs/workflows/simsetup.py
aiida_gromacs-2.1.1.dist-info/entry_points.txt
aiida_gromacs-2.1.1.dist-info/licenses/LICENSE
aiida_gromacs-2.1.1.dist-info/WHEEL
aiida_gromacs-2.1.1.dist-info/METADATA
aiida_gromacs-2.1.1.dist-info/RECORD
