Metadata-Version: 2.4
Name: aiida-gromacs
Version: 2.1.1
Summary: A plugin for using GROMACS with AiiDA for molecular dymanics simulations.
Keywords: aiida,plugin,gromacs,aiida-gromacs
Author-email: James Gebbie-Rayet <james.gebbie@stfc.ac.uk>, Jas Kalayan <jas.kalayan@stfc.ac.uk>
Requires-Python: >=3.8
Classifier: Programming Language :: Python
Classifier: Programming Language :: Python :: 3.11
Classifier: Intended Audience :: Science/Research
Classifier: License :: OSI Approved :: MIT License
Classifier: Natural Language :: English
Classifier: Development Status :: 5 - Production/Stable
Classifier: Framework :: AiiDA
License-File: LICENSE
Requires-Dist: aiida-core>=2.5.0,<=2.6.3
Requires-Dist: voluptuous
Requires-Dist: sphinx ; extra == "docs"
Requires-Dist: sphinx_rtd_theme ; extra == "docs"
Requires-Dist: sphinxcontrib-contentui ; extra == "docs"
Requires-Dist: sphinxcontrib-details-directive ; extra == "docs"
Requires-Dist: sphinx_copybutton ; extra == "docs"
Requires-Dist: furo ; extra == "docs"
Requires-Dist: markupsafe<2.1 ; extra == "docs"
Requires-Dist: pre-commit==3.7.1 ; extra == "pre-commit"
Requires-Dist: pylint==3.2.5 ; extra == "pre-commit"
Requires-Dist: pgtest==1.3.2 ; extra == "testing"
Requires-Dist: wheel==0.43.0 ; extra == "testing"
Requires-Dist: coverage[toml] ; extra == "testing"
Requires-Dist: pytest==8.2.2 ; extra == "testing"
Requires-Dist: pytest-cov==5.0.0 ; extra == "testing"
Requires-Dist: pytest-sugar==1.0.0 ; extra == "testing"
Project-URL: Source, https://github.com/CCPBioSim/aiida-gromacs
Provides-Extra: docs
Provides-Extra: pre-commit
Provides-Extra: testing
